paper_bartender/__init__.py
paper_bartender/cli/__init__.py
paper_bartender/cli/add.py
paper_bartender/cli/app.py
paper_bartender/cli/delete.py
paper_bartender/cli/list.py
paper_bartender/config/__init__.py
paper_bartender/config/settings.py
paper_bartender/models/__init__.py
paper_bartender/models/milestone.py
paper_bartender/models/paper.py
paper_bartender/models/storage.py
paper_bartender/models/task.py
paper_bartender/services/__init__.py
paper_bartender/services/decomposition.py
paper_bartender/services/milestone_service.py
paper_bartender/services/nlp_parser.py
paper_bartender/services/paper_service.py
paper_bartender/services/task_service.py
paper_bartender/storage/__init__.py
paper_bartender/storage/json_store.py
paper_bartender/utils/__init__.py
paper_bartender/utils/dates.py
paper_bartender/utils/display.py
paper_bartender/utils/pdf.py
paper_bartender-0.1.0.dist-info/METADATA
paper_bartender-0.1.0.dist-info/WHEEL
paper_bartender-0.1.0.dist-info/entry_points.txt
paper_bartender-0.1.0.dist-info/licenses/LICENSE
paper_bartender-0.1.0.dist-info/RECORD
