Metadata-Version: 2.4
Name: paper-bartender
Version: 0.1.0
Summary: A CLI tool to help researchers manage paper deadlines by decomposing milestones into daily tasks
License: Apache-2.0
License-File: LICENSE
Keywords: cli,research,paper,deadline,task,ai,productivity
Author: Haofei Yu
Author-email: yuhaofei44@gmail.com
Requires-Python: >=3.9,<3.13
Classifier: Development Status :: 4 - Beta
Classifier: Environment :: Console
Classifier: Intended Audience :: Science/Research
Classifier: License :: OSI Approved :: Apache Software License
Classifier: Operating System :: OS Independent
Classifier: Programming Language :: Python :: 3
Classifier: Programming Language :: Python :: 3.9
Classifier: Programming Language :: Python :: 3.10
Classifier: Programming Language :: Python :: 3.11
Classifier: Programming Language :: Python :: 3.12
Classifier: Topic :: Scientific/Engineering
Classifier: Topic :: Utilities
Requires-Dist: anthropic (>=0.40.0,<0.41.0)
Requires-Dist: openai (>=1.0.0,<2.0.0)
Requires-Dist: pydantic (>=2.8.2,<3.0.0)
Requires-Dist: pydantic-settings (>=2.4.0,<3.0.0)
Requires-Dist: pymupdf (>=1.24.0,<2.0.0)
Requires-Dist: python-dateutil (>=2.9.0,<3.0.0)
Requires-Dist: typer[all] (>=0.12.0,<0.13.0)
Project-URL: Homepage, https://github.com/lwaekfjlk/paper-bartender
Project-URL: Repository, https://github.com/lwaekfjlk/paper-bartender
